nonebot_session_to_uninfo/__init__.py
nonebot_session_to_uninfo-0.0.2.dist-info/LICENSE
nonebot_session_to_uninfo-0.0.2.dist-info/METADATA
nonebot_session_to_uninfo-0.0.2.dist-info/WHEEL
nonebot_session_to_uninfo-0.0.2.dist-info/RECORD
