Metadata-Version: 2.1
Name: nonebot_session_to_uninfo
Version: 0.0.2
Summary: session 插件到 uninfo 插件的 orm 迁移工具
Home-page: https://github.com/noneplugin/nonebot-session-to-uninfo
License: MIT
Author: meetwq
Author-email: meetwq@gmail.com
Requires-Python: >=3.9,<4.0
Classifier: License :: OSI Approved :: MIT License
Classifier: Programming Language :: Python :: 3
Classifier: Programming Language :: Python :: 3.9
Classifier: Programming Language :: Python :: 3.10
Classifier: Programming Language :: Python :: 3.11
Classifier: Programming Language :: Python :: 3.12
Classifier: Programming Language :: Python :: 3.13
Requires-Dist: alembic (>=1.13,<2.0)
Requires-Dist: sqlalchemy (>=2.0,<3.0)
Requires-Dist: strenum (>=0.4.15,<0.5.0)
Project-URL: Repository, https://github.com/noneplugin/nonebot-session-to-uninfo
